LICENSE
README.md
lookup_fields/__init__.py
lookup_fields/fields.py
lookup_fields/locale/en/LC_MESSAGES/django.po
lookup_fields/locale/pl/LC_MESSAGES/django.po
lookup_fields/permissions.py
lookup_fields/serializers.py
lookup_fields/views.py
drf_lookup_fields-1.1.0.dist-info/LICENSE
drf_lookup_fields-1.1.0.dist-info/WHEEL
drf_lookup_fields-1.1.0.dist-info/METADATA
drf_lookup_fields-1.1.0.dist-info/RECORD
