Metadata-Version: 2.1
Name: drf-lookup-fields
Version: 1.1.0
Summary: A package supplying tools for custom foreign-key fields lookup in drf-created WebAPI.
Home-page: https://github.com/innovationinit/drf-lookup-fields
License: BSD-2-Clause
Author: IIIT
Author-email: github@iiit.pl
Requires-Python: >=3.7,<3.10
Classifier: License :: OSI Approved :: BSD License
Classifier: Programming Language :: Python :: 3
Classifier: Programming Language :: Python :: 3.7
Classifier: Programming Language :: Python :: 3.8
Classifier: Programming Language :: Python :: 3.9
Requires-Dist: Django (>=2.0,<4.0)
Requires-Dist: djangorestframework (>=3.3.2)
Project-URL: Repository, https://github.com/innovationinit/drf-lookup-fields
